{"title":"REXP DotJs 2020","description":"Nous vous proposons un retour sur notre participation à DotJs 2019 à Paris. Au programme : * présentation de l’événement * retour sur les conférences * points d&#x27;attentions sur nos coup de cœur ","video":"https://youtu.be/KD7rj2puboc","speakers":[{"id":"j8jeenJ4PhVKLMvNIlQehGkiy2Y2","name":"Anthony PENA","link":"_Anthony_Pena"},{"id":"gNtq1ymBngUhrtRzDSmA0gEWgEX2","name":"Adrien LASSELLE","link":"AdrienLASSELLE"}],"href":"/talks/iEjtPtLKhmJMKX38y38t.json","id":"iEjtPtLKhmJMKX38y38t"}